control_lab_ly-2.1.0.dist-info/licenses/LICENSE.md
controllably/__init__.py
controllably/__main__.py
controllably/py.typed
controllably/readme.md
controllably/Compound/__init__.py
controllably/Compound/LiquidMover/__init__.py
controllably/Compound/LiquidMover/liquidmover.py
controllably/Compound/VacuumMover/__init__.py
controllably/Compound/VacuumMover/vacuummover.py
controllably/Make/__init__.py
controllably/Make/make.py
controllably/Make/Heat/__init__.py
controllably/Make/Heat/heater_mixin.py
controllably/Make/Heat/peltier.py
controllably/Make/Light/__init__.py
controllably/Make/Light/led.py
controllably/Make/Mixture/__init__.py
controllably/Make/Mixture/QInstruments/__init__.py
controllably/Make/Mixture/QInstruments/bioshake.py
controllably/Make/Mixture/QInstruments/qinstruments_api/__init__.py
controllably/Make/Mixture/QInstruments/qinstruments_api/qinstruments_api.py
controllably/Make/Mixture/QInstruments/qinstruments_api/qinstruments_lib.py
controllably/Make/Mixture/TwoMag/__init__.py
controllably/Make/Mixture/TwoMag/twomag.py
controllably/Make/Mixture/TwoMag/twomag_api/__init__.py
controllably/Make/Mixture/TwoMag/twomag_api/twomag_api.py
controllably/Make/Mixture/TwoMag/twomag_api/twomag_lib.py
controllably/Make/ThinFilm/__init__.py
controllably/Make/ThinFilm/spinner.py
controllably/Make/Vacuum/__init__.py
controllably/Make/Vacuum/vacuum_mixin.py
controllably/Measure/__init__.py
controllably/Measure/measure.py
controllably/Measure/Chemical/__init__.py
controllably/Measure/Chemical/Sentron/__init__.py
controllably/Measure/Chemical/Sentron/sentron.py
controllably/Measure/Electrical/__init__.py
controllably/Measure/Electrical/BioLogic/__init__.py
controllably/Measure/Electrical/BioLogic/biologic.py
controllably/Measure/Electrical/Keithley/__init__.py
controllably/Measure/Electrical/Keithley/keithley.py
controllably/Measure/Electrical/Keithley/programs/__init__.py
controllably/Measure/Electrical/Keithley/programs/base_programs.py
controllably/Measure/Mechanical/__init__.py
control_lab_ly-2.1.0.dist-info/METADATA
control_lab_ly-2.1.0.dist-info/WHEEL
control_lab_ly-2.1.0.dist-info/top_level.txt
control_lab_ly-2.1.0.dist-info/RECORD
