Metadata-Version: 2.4
Name: control-lab-ly
Version: 2.1.0
Summary: Lab Equipment Automation Package
Author-email: Chang Jie Leong <changjie.leong@outlook.com>
License-Expression: MIT
Project-URL: Homepage, https://kylejeanlewis.github.io/control-lab-ly/
Project-URL: GitHub, https://github.com/kylejeanlewis/control-lab-ly
Project-URL: Documentation, https://control-lab-ly.readthedocs.io/en/latest/
Project-URL: Changelog, https://github.com/kylejeanlewis/control-lab-ly/blob/main/docs/CHANGELOG.md
Project-URL: Tracker, https://github.com/kylejeanlewis/control-lab-ly/issues
Keywords: python,lab automation
Classifier: Development Status :: 3 - Alpha
Classifier: Intended Audience :: Developers
Classifier: Intended Audience :: Science/Research
Classifier: Operating System :: Microsoft :: Windows
Classifier: Programming Language :: Python :: 3
Classifier: Programming Language :: Python :: 3 :: Only
Classifier: Programming Language :: Python :: 3.10
Classifier: Programming Language :: Python :: 3.11
Classifier: Programming Language :: Python :: 3.12
Classifier: Topic :: Scientific/Engineering
Requires-Python: >=3.10
License-File: LICENSE.md
Requires-Dist: matplotlib>=3.9
Requires-Dist: numpy>=2.0
Requires-Dist: opencv_python>=4.10.0
Requires-Dist: pandas>=2.0
Requires-Dist: parse>=1.20
Requires-Dist: pyserial>=3.5
Requires-Dist: PyYAML>=6.0.1
Requires-Dist: scipy>=1.14
Requires-Dist: websockets>=15.0.1
Provides-Extra: dev
Requires-Dist: pytest>=7.4; extra == "dev"
Requires-Dist: pytest-cov>=2.11; extra == "dev"
Requires-Dist: pytest-rerunfailures>=15.0; extra == "dev"
Requires-Dist: pytest-xdist>=3.6; extra == "dev"
Requires-Dist: tox>=4.27; extra == "dev"
Provides-Extra: docs
Requires-Dist: mkdocs>=1.6.1; extra == "docs"
Requires-Dist: mkdocs-material>=9.6.14; extra == "docs"
Requires-Dist: mkdocstrings-python>=1.16.12; extra == "docs"
Requires-Dist: ruff>=0.12.0; extra == "docs"
Provides-Extra: all
Requires-Dist: pyModbusTCP>=0.2; extra == "all"
Requires-Dist: easy-biologic>=0.4.0; extra == "all"
Requires-Dist: nest-asyncio>=1.6.0; extra == "all"
Requires-Dist: setuptools>=71.0.3; extra == "all"
Requires-Dist: PyMeasure>=0.15; extra == "all"
Provides-Extra: ax8
Requires-Dist: pyModbusTCP>=0.2; extra == "ax8"
Provides-Extra: biologic
Requires-Dist: easy-biologic>=0.4.0; extra == "biologic"
Requires-Dist: nest-asyncio>=1.6.0; extra == "biologic"
Requires-Dist: setuptools>=71.0.3; extra == "biologic"
Provides-Extra: keithley
Requires-Dist: PyMeasure>=0.15; extra == "keithley"
Dynamic: license-file
